Workbook

Sheet Transactions
A1: Date | B1: Type | C1: Category | D1: Description | E1: Amount | F1: BS Account
A2: 46093.591 | B2: EXPENSE | C2: Marketing | E2: 500 | F2: Cash & Cash Equivalents

Sheet Balance Sheet
B1: BALANCE SHEET
B2: As-Of Date: | C2: 46093.771
B4: ASSETS
B5: Current Assets
B6: Cash & Cash Equivalents | C6: =SUMIFS(Transactions!$E$2:$E$2,Transactions!$B$2:$B$2,"INCOME",Transactions!$F$2:$F$2,"Cash & Cash Equivalents")-SUMIFS(Transactions!$E$2:$E$2,Transactions!$B$2:$B$2,"EXPENSE",Transactions!$F$2:$F$2,"Cash & Cash Equivalents")-SUMIFS(Transactions!$E$2:$E$2,Transactions!$B$2:$B$2,"EXPENSE",Transactions!$F$2:$F$2,"Property, Plant & Equipment")-SUMIFS(Transactions!$E$2:$E$2,Transactions!$B$2:$B$2,"EXPENSE",Transactions!$F$2:$F$2,"Intangible Assets")-SUMIFS(Transactions!$E$2:$E$2,Transactions!$B$2:$B$2,"EXPENSE",Transactions!$F$2:$F$2,"Inventory")-SUMIFS(Transactions!$E$2:$E$2,Transactions!$B$2:$B$2,"EXPENSE",Transactions!$F$2:$F$2,"Prepaid Expenses")
B7: Accounts Receivable | C7: =SUMIFS(Transactions!$E$2:$E$2,Transactions!$F$2:$F$2,"Accounts Receivable")
B8: Inventory | C8: =SUMIFS(Transactions!$E$2:$E$2,Transactions!$F$2:$F$2,"Inventory")
B9: Prepaid Expenses | C9: =SUMIFS(Transactions!$E$2:$E$2,Transactions!$F$2:$F$2,"Prepaid Expenses")
B10: Total Current Assets | C10: =SUM(C6:C9)
B12: Non-Current Assets
B13: Property, Plant & Equipment | C13: =SUMIFS(Transactions!$E$2:$E$2,Transactions!$F$2:$F$2,"Property, Plant & Equipment")
B14: Intangible Assets | C14: =SUMIFS(Transactions!$E$2:$E$2,Transactions!$F$2:$F$2,"Intangible Assets")
B15: Total Non-Current Assets | C15: =SUM(C13:C14)
B17: TOTAL ASSETS | C17: =C10+C15
B19: LIABILITIES
B20: Current Liabilities
B21: Accounts Payable | C21: =SUMIFS(Transactions!$E$2:$E$2,Transactions!$F$2:$F$2,"Accounts Payable")
B22: Accrued Expenses | C22: =SUMIFS(Transactions!$E$2:$E$2,Transactions!$F$2:$F$2,"Accrued Expenses")
B23: Salaries Payable | C23: =SUMIFS(Transactions!$E$2:$E$2,Transactions!$F$2:$F$2,"Salaries Payable")
B24: Short-Term Debt | C24: =SUMIFS(Transactions!$E$2:$E$2,Transactions!$F$2:$F$2,"Short-Term Debt")
B25: Total Current Liabilities | C25: =SUM(C21:C24)
B27: Non-Current Liabilities
B28: Long-Term Debt | C28: =SUMIFS(Transactions!$E$2:$E$2,Transactions!$F$2:$F$2,"Long-Term Debt")
B29: Deferred Tax Liability | C29: =SUMIFS(Transactions!$E$2:$E$2,Transactions!$F$2:$F$2,"Deferred Tax Liability")
B30: Total Non-Current Liabilities | C30: =SUM(C28:C29)
B32: TOTAL LIABILITIES | C32: =C25+C30
B34: EQUITY
B35: Shareholders' Equity
B36: Share Capital | C36: =SUMIFS(Transactions!$E$2:$E$2,Transactions!$F$2:$F$2,"Share Capital")
B37: Retained Earnings | C37: =SUMIFS(Transactions!$E$2:$E$2,Transactions!$B$2:$B$2,"INCOME")-SUMIFS(Transactions!$E$2:$E$2,Transactions!$B$2:$B$2,"EXPENSE")
B38: Total Shareholders' Equity | C38: =SUM(C36:C37)
B40: TOTAL EQUITY | C40: =C38
B43: Balance Check (A - L - E) | C43: =C17-C32-C40
